src/game_of_life.vhd
LIBRARY ieee;
USE ieee.std_logic_1164.ALL;
USE ieee.math_real.ALL;
USE ieee.numeric_std.ALL;
USE ieee.std_logic_unsigned.ALL;
USE ieee.numeric_std.ALL;
USE std.textio.ALL;

ENTITY game_of_life IS
    PORT (
        clk : IN STD_LOGIC := '0';
        start : IN STD_LOGIC := '0'
    );
END ENTITY;

ARCHITECTURE arch OF game_of_life IS
    CONSTANT W : INTEGER := 15;
    CONSTANT H : INTEGER := 15;
    CONSTANT max_tick : INTEGER := 30;
    CONSTANT portion_size : INTEGER := W; -- max W
    CONSTANT seed1 : POSITIVE := 3;
    CONSTANT seed2 : POSITIVE := 7;
    CONSTANT filename : STRING := "output/game_of_life.txt";

    TYPE init_map_type IS ARRAY (0 TO (H - 1)) OF STD_LOGIC_VECTOR(0 TO (W - 1));
    TYPE init_state_type IS (random, glider, achim_p4, crystal, achim_p16, custom);
    CONSTANT init_state : init_state_type := random; --achim_p16;-- glider; -- achim_p4;

    CONSTANT achim_p16_init_map : init_map_type := (
        "000000001100000",
        "000000001010000",
        "000100001011000",
        "001100000100000",
        "010010000000000",
        "011100000000000",
        "000000000000000",
        "000000000001110",
        "000000000010010",
        "000000000001100",
        "000001000001000",
        "000110100000000",
        "000010100000000",
        "000001100000000",
        "000000000000000"
    );

    CONSTANT crystal_init_map: init_map_type := (
        "000000000000000",
        "000000000000000",
        "000010000000000",
        "000001000110000",
        "000111000110000",
        "000000000000000",
        "000000000000000",
        "000000000000000",
        "000000000000000",
        "000000000000000",
        "000000000000000",
        "000000000000000",
        "000000000000000",
        "000000000000000",
        "000000000000000"
    );

    CONSTANT achim_p4_init_map: init_map_type := (
        "000000010000000",
        "000000101000000",
        "000001010100000",
        "000001000100000",
        "001101010101100",
        "001010000010100",
        "000001111100000",
        "000000000000000",
        "000000010000000",
        "000000101000000",
        "000000010000000",
        "000000000000000",
        "000000000000000",
        "000000000000000",
        "000000000000000"
    );
    
    CONSTANT glider_init_map : init_map_type := ( 
        "010000000000000",
        "001000000000000",
        "111000000000000",
        OTHERS => (others => '0')
    );

    CONSTANT custom_init_map : init_map_type := ( 
        "110000000000000",
        "001000000000000",
        OTHERS => (others => '0')
    );

    SIGNAL init_map : init_map_type := (OTHERS => (OTHERS => '0'));

    -- map padded with zeros for calculations
    TYPE reg_map_type IS ARRAY (0 TO (H + 1)) OF STD_LOGIC_VECTOR(0 TO (W + 1));
    SIGNAL curr_map : reg_map_type := (OTHERS => (OTHERS => '0'));
    SIGNAL new_map : reg_map_type := (OTHERS => (OTHERS => '0'));

    SIGNAL tick : INTEGER := 0;
    SIGNAL row_count : INTEGER := 0;
    SIGNAL col_count : INTEGER := 0;

    -- 3 x Width row_blocks of the map
    -- MSB and LSB should be changed? This way its easier to iterate in loops. 
    TYPE row_block_type IS ARRAY (0 TO 2) OF STD_LOGIC_VECTOR(0 TO (W + 1));
    SIGNAL row_block : row_block_type;

    -- a portion of the row_block
    TYPE portion_type IS ARRAY (0 TO 2) OF STD_LOGIC_VECTOR(0 TO (portion_size + 1));
    SIGNAL portion : portion_type;

    TYPE block_type IS ARRAY (0 TO 2) OF STD_LOGIC_VECTOR(0 TO 2);

    -- state memory (SM)
    TYPE state_type IS (init, load_row, load_portion, eval_portion, calculated);
    SIGNAL state : state_type := init;

    -- generate random init map
    FUNCTION generate_init_map RETURN init_map_type IS
        VARIABLE s1 : POSITIVE := seed1;
        VARIABLE s2 : POSITIVE := seed2;
        VARIABLE re : REAL;
        VARIABLE new_init_map : init_map_type;
    BEGIN
        FOR i IN 0 TO (H - 1) LOOP
            FOR j IN 0 TO (W - 1) LOOP
                uniform(s1, s2, re);
                new_init_map(i)(j) := '1' WHEN re > 0.5 ELSE
                '0';
            END LOOP;
        END LOOP;
        RETURN new_init_map;
    END FUNCTION;
BEGIN
    PROCESS (clk, start)
        VARIABLE living_count : INTEGER := 0; -- need in computation step
        VARIABLE block3x3 : block_type := (OTHERS => (OTHERS => '0')); -- to easily debug the computation step  
        VARIABLE new_n, new_m : INTEGER := 0; -- indexes for the new map
        VARIABLE row : STD_LOGIC_VECTOR(0 TO W - 1); -- tmp just for output the non padded map
        FILE out_file : text; -- for file output
        VARIABLE out_line : line; -- for file output
    BEGIN
        IF rising_edge(clk) THEN
            CASE state IS
                WHEN init =>
                    -- next state logic (NSL) 
                    IF (start = '1') THEN
                        state <= load_row;
                    ELSE
                        state <= init;
                    END IF;

                    -- out function logic (OFL)

                    -- if random map enabled, generate random map
                    CASE init_state IS
                        WHEN glider => init_map <= glider_init_map;
                        WHEN achim_p4 => init_map <= achim_p4_init_map;
                        WHEN achim_p16 => init_map <= achim_p16_init_map;
                        WHEN crystal => init_map <= crystal_init_map;
                        WHEN random => init_map <= generate_init_map;
                        WHEN custom => init_map <= custom_init_map;
                        WHEN OTHERS => null;
                    END CASE;

                    IF start = '1' THEN
                        file_open(out_file, filename, write_mode);
                        -- put init map into reg_map
                        FOR i IN 1 TO H LOOP
                            FOR j IN 1 TO W LOOP
                                curr_map(i)(j) <= init_map(i - 1)(j - 1);
                            END LOOP;
                        END LOOP;
                    END IF;

                WHEN load_row =>
                    -- NSL
                    IF row_count < H THEN
                        state <= load_portion;
                    ELSE
                        state <= calculated;
                    END IF;

                    -- OFL
                    IF row_count < H THEN
                        col_count <= 0;

                        -- fill row_block
                        FOR i IN 0 TO 2 LOOP
                            row_block(i) <= curr_map(row_count + i);
                            -- report to_string(row_block(i));
                        END LOOP;
                        row_count <= row_count + 1;
                    END IF;
                WHEN load_portion =>
                    -- NSL
                    IF col_count < W THEN
                        state <= eval_portion;
                    ELSE
                        state <= load_row;
                    END IF;

                    -- OFL 
                    IF col_count < W THEN
                        -- fill portion
                        FOR i IN 0 TO 2 LOOP
                            FOR j IN col_count TO col_count + portion_size + 1 LOOP
                                IF j < W + 2 THEN
                                    portion(i)(j - col_count) <= row_block(i)(j);
                                END IF;
                            END LOOP;
                            -- REPORT to_string(portion(i));
                        END LOOP; -- fill_portion

                        col_count <= col_count + portion_size;
                    END IF;
                WHEN eval_portion =>
                    -- NSL
                    state <= load_portion;

                    -- OFL
                    -- loop through portions

                    FOR i IN 0 TO portion_size - 1 LOOP
                        IF (col_count - portion_size) + i < W THEN
                            new_n := row_count;
                            new_m := (col_count - portion_size) + i + 1;
                            living_count := 0;

                            -- report "n: " & to_string(new_n) & " m: " & to_string(new_m);

                            -- assign block
                            FOR n IN 0 TO 2 LOOP
                                FOR m IN 0 TO 2 LOOP
                                    block3x3(n)(m) := portion(n)(i + m);
                                END LOOP;
                            END LOOP;

                            -- for n in 0 to 2 loop
                            --     report to_string(block3x3(n));
                            -- end loop;

                            -- count living cells
                            FOR n IN 0 TO 2 LOOP
                                FOR m IN 0 TO 2 LOOP
                                    IF NOT (n = 1 AND m = 1) AND block3x3(n)(m) = '1' THEN
                                        living_count := living_count + 1;
                                    END IF;
                                END LOOP;
                            END LOOP;
                            -- report to_string(living_count);

                            -- assign value to new_map based on living_count
                            CASE block3x3(1)(1) IS
                                WHEN '1' =>
                                    CASE living_count IS
                                        WHEN 2 | 3 => new_map(new_n)(new_m) <= '1';
                                        WHEN OTHERS => new_map(new_n)(new_m) <= '0';
                                    END CASE;
                                WHEN '0' =>
                                    CASE living_count IS
                                        WHEN 3 => new_map(new_n)(new_m) <= '1';
                                        WHEN OTHERS => new_map(new_n)(new_m) <= '0';
                                    END CASE;
                                WHEN OTHERS => NULL;
                            END CASE;
                        END IF;
                    END LOOP;
                    -- report to_string(new_map(row_count));
                WHEN calculated =>
                    -- NSL
                    IF tick < max_tick - 1 THEN
                        state <= load_row;
                    ELSE
                        state <= init;
                    END IF;

                    -- OFL
                    row_count <= 0;
                    tick <= tick + 1;
                    curr_map <= new_map;

                    FOR i IN 1 TO H LOOP
                        FOR j IN 0 TO W - 1 LOOP
                            row(j) := curr_map(i)(j + 1);
                        END LOOP;
                        REPORT to_string(row);
                        IF (i /= H) THEN
                            write(out_line, row);
                            writeline(out_file, out_line);
                        ELSE
                            write(out_line, row);
                        END IF;
                    END LOOP;
                    REPORT "";
                    write(out_line, lf);
                    writeline(out_file, out_line);
                WHEN OTHERS =>
                    -- NSL
                    state <= init;
            END CASE;
        END IF;
    END PROCESS;
END ARCHITECTURE; -- arch

src/game_of_life_tb.vhd
LIBRARY ieee;
USE ieee.std_logic_1164.ALL;

ENTITY game_of_life_tb IS
END ENTITY;

ARCHITECTURE arch OF game_of_life_tb IS
    COMPONENT game_of_life IS
    PORT (
        clk : IN STD_LOGIC := '0';
        start : IN STD_LOGIC := '0'
    );
    END COMPONENT;

    CONSTANT clk_period : TIME := 10 ns;
    SIGNAL clk : STD_LOGIC := '0';
    signal start : std_logic := '0';
    
BEGIN
    uut : game_of_life 
    PORT MAP(
        clk => clk,
        start => start
    );

    clk_gen : PROCESS
    BEGIN
        FOR i IN 1 TO 50000 LOOP
            clk <= '0';
            WAIT FOR clk_period/2;
            clk <= '1';
            WAIT FOR clk_period/2;
        END LOOP;
        WAIT;
    END PROCESS; -- stim

    stim : PROCESS
    BEGIN
        wait for 100 ns;

        start <= '1';   
        wait for 5 * clk_period;
        start <= '0';
        wait;
    END PROCESS;
END ARCHITECTURE; -- arch

src/output/game_of_life_tb.vcd
$date
  Mon Jan 25 10:08:45 2021
$end
$version
  GHDL v0
$end
$timescale
  1 fs
$end
$scope module standard $end
$upscope $end
$scope module textio $end
$upscope $end
$scope module std_logic_1164 $end
$upscope $end
$scope module math_real $end
$upscope $end
$scope module numeric_std $end
$upscope $end
$scope module std_logic_arith $end
$upscope $end
$scope module std_logic_unsigned $end
$upscope $end
$scope module game_of_life_tb $end
$var reg 1 ! clk $end
$var reg 1 " start $end
$scope module uut $end
$var reg 1 # clk $end
$var reg 1 $ start $end
$comment init_map is not handled $end
$comment curr_map is not handled $end
$comment new_map is not handled $end
$var integer 32 % tick $end
$var integer 32 & row_count $end
$var integer 32 ' col_count $end
$comment row_block is not handled $end
$comment portion is not handled $end
$comment state is not handled $end
$upscope $end
$upscope $end
$enddefinitions $end
#0
0!
0"
0#
0$
b0 %
b0 &
b0 '
#5000000
1!
1#
#10000000
0!
0#
#15000000
1!
1#
#20000000
0!
0#
#25000000
1!
1#
#30000000
0!
0#
#35000000
1!
1#
#40000000
0!
0#
#45000000
1!
1#
#50000000
0!
0#
#55000000
1!
1#
#60000000
0!
0#
#65000000
1!
1#
#70000000
0!
0#
#75000000
1!
1#
#80000000
0!
0#
#85000000
1!
1#
#90000000
0!
0#
#95000000
1!
1#
#100000000
0!
1"
0#
1$
#105000000
1!
1#
#110000000
0!
0#
#115000000
1!
1#
b1 &
#120000000
0!
0#
#125000000
1!
1#
b1111 '
#130000000
0!
0#
#135000000
1!
1#
#140000000
0!
0#
#145000000
1!
1#
#150000000
0!
0"
0#
0$
#155000000
1!
1#
b10 &
b0 '
#160000000
0!
0#
#165000000
1!
1#
b1111 '
#170000000
0!
0#
#175000000
1!
1#
#180000000
0!
0#
#185000000
1!
1#
#190000000
0!
0#
#195000000
1!
1#
b11 &
b0 '
#200000000
0!
0#
#205000000
1!
1#
b1111 '
#210000000
0!
0#
#215000000
1!
1#
#220000000
0!
0#
#225000000
1!
1#
#230000000
0!
0#
#235000000
1!
1#
b100 &
b0 '
#240000000
0!
0#
#245000000
1!
1#
b1111 '
#250000000
0!
0#
#255000000
1!
1#
#260000000
0!
0#
#265000000
1!
1#
#270000000
0!
0#
#275000000
1!
1#
b101 &
b0 '
#280000000
0!
0#
#285000000
1!
1#
b1111 '
#290000000
0!
0#
#295000000
1!
1#
#300000000
0!
0#
#305000000
1!
1#
#310000000
0!
0#
#315000000
1!
1#
b110 &
b0 '
#320000000
0!
0#
#325000000
1!
1#
b1111 '
#330000000
0!
0#
#335000000
1!
1#
#340000000
0!
0#
#345000000
1!
1#
#350000000
0!
0#
#355000000
1!
1#
b111 &
b0 '
#360000000
0!
0#
#365000000
1!
1#
b1111 '
#370000000
0!
0#
#375000000
1!
1#
#380000000
0!
0#
#385000000
1!
1#
#390000000
0!
0#
#395000000
1!
1#
b1000 &
b0 '
#400000000
0!
0#
#405000000
1!
1#
b1111 '
#410000000
0!
0#
#415000000
1!
1#
#420000000
0!
0#
#425000000
1!
1#
#430000000
0!
0#
#435000000
1!
1#
b1001 &
b0 '
#440000000
0!
0#
#445000000
1!
1#
b1111 '
#450000000
0!
0#
#455000000
1!
1#
#460000000
0!
0#
#465000000
1!
1#
#470000000
0!
0#
#475000000
1!
1#
b1010 &
b0 '
#480000000
0!
0#
#485000000
1!
1#
b1111 '
#490000000
0!
0#
#495000000
1!
1#
#500000000
0!
0#
#505000000
1!
1#
#510000000
0!
0#
#515000000
1!
1#
b1011 &
b0 '
#520000000
0!
0#
#525000000
1!
1#
b1111 '
#530000000
0!
0#
#535000000
1!
1#
#540000000
0!
0#
#545000000
1!
1#
#550000000
0!
0#
#555000000
1!
1#
b1100 &
b0 '
#560000000
0!
0#
#565000000
1!
1#
b1111 '
#570000000
0!
0#
#575000000
1!
1#
#580000000
0!
0#
#585000000
1!
1#
#590000000
0!
0#
#595000000
1!
1#
b1101 &
b0 '
#600000000
0!
0#
#605000000
1!
1#
b1111 '
#610000000
0!
0#
#615000000
1!
1#
#620000000
0!
0#
#625000000
1!
1#
#630000000
0!
0#
#635000000
1!
1#
b1110 &
b0 '
#640000000
0!
0#
#645000000
1!
1#
b1111 '
#650000000
0!
0#
#655000000
1!
1#
#660000000
0!
0#
#665000000
1!
1#
#670000000
0!
0#
#675000000
1!
1#
b1111 &
b0 '
#680000000
0!
0#
#685000000
1!
1#
b1111 '
#690000000
0!
0#
#695000000
1!
1#
#700000000
0!
0#
#705000000
1!
1#
#710000000
0!
0#
#715000000
1!
1#
#720000000
0!
0#
#725000000
1!
1#
b1 %
b0 &
#730000000
0!
0#
#735000000
1!
1#
b1 &
b0 '
#740000000
0!
0#
#745000000
1!
1#
b1111 '
#750000000
0!
0#
#755000000
1!
1#
#760000000
0!
0#
#765000000
1!
1#
#770000000
0!
0#
#775000000
1!
1#
b10 &
b0 '
#780000000
0!
0#
#785000000
1!
1#
b1111 '
#790000000
0!
0#
#795000000
1!
1#
#800000000
0!
0#
#805000000
1!
1#
#810000000
0!
0#
#815000000
1!
1#
b11 &
b0 '
#820000000
0!
0#
#825000000
1!
1#
b1111 '
#830000000
0!
0#
#835000000
1!
1#
#840000000
0!
0#
#845000000
1!
1#
#850000000
0!
0#
#855000000
1!
1#
b100 &
b0 '
#860000000
0!
0#
#865000000
1!
1#
b1111 '
#870000000
0!
0#
#875000000
1!
1#
#880000000
0!
0#
#885000000
1!
1#
#890000000
0!
0#
#895000000
1!
1#
b101 &
b0 '
#900000000
0!
0#
#905000000
1!
1#
b1111 '
#910000000
0!
0#
#915000000
1!
1#
#920000000
0!
0#
#925000000
1!
1#
#930000000
0!
0#
#935000000
1!
1#
b110 &
b0 '
#940000000
0!
0#
#945000000
1!
1#
b1111 '
#950000000
0!
0#
#955000000
1!
1#
#960000000
0!
0#
#965000000
1!
1#
#970000000
0!
0#
#975000000
1!
1#
b111 &
b0 '
#980000000
0!
0#
#985000000
1!
1#
b1111 '
#990000000
0!
0#
#995000000
1!
1#
#1000000000
0!
0#
#1005000000
1!
1#
#1010000000
0!
0#
#1015000000
1!
1#
b1000 &
b0 '
#1020000000
0!
0#
#1025000000
1!
1#
b1111 '
#1030000000
0!
0#
#1035000000
1!
1#
#1040000000
0!
0#
#1045000000
1!
1#
#1050000000
0!
0#
#1055000000
1!
1#
b1001 &
b0 '
#1060000000
0!
0#
#1065000000
1!
1#
b1111 '
#1070000000
0!
0#
#1075000000
1!
1#
#1080000000
0!
0#
#1085000000
1!
1#
#1090000000
0!
0#
#1095000000
1!
1#
b1010 &
b0 '
#1100000000
0!
0#
#1105000000
1!
1#
b1111 '
#1110000000
0!
0#
#1115000000
1!
1#
#1120000000
0!
0#
#1125000000
1!
1#
#1130000000
0!
0#
#1135000000
1!
1#
b1011 &
b0 '
#1140000000
0!
0#
#1145000000
1!
1#
b1111 '
#1150000000
0!
0#
#1155000000
1!
1#
#1160000000
0!
0#
#1165000000
1!
1#
#1170000000
0!
0#
#1175000000
1!
1#
b1100 &
b0 '
#1180000000
0!
0#
#1185000000
1!
1#
b1111 '
#1190000000
0!
0#
#1195000000
1!
1#
#1200000000
0!
0#
#1205000000
1!
1#
#1210000000
0!
0#
#1215000000
1!
1#
b1101 &
b0 '
#1220000000
0!
0#
#1225000000
1!
1#
b1111 '
#1230000000
0!
0#
#1235000000
1!
1#
#1240000000
0!
0#
#1245000000
1!
1#
#1250000000
0!
0#
#1255000000
1!
1#
b1110 &
b0 '
#1260000000
0!
0#
#1265000000
1!
1#
b1111 '
#1270000000
0!
0#
#1275000000
1!
1#
#1280000000
0!
0#
#1285000000
1!
1#
#1290000000
0!
0#
#1295000000
1!
1#
b1111 &
b0 '
#1300000000
0!
0#
#1305000000
1!
1#
b1111 '
#1310000000
0!
0#
#1315000000
1!
1#
#1320000000
0!
0#
#1325000000
1!
1#
#1330000000
0!
0#
#1335000000
1!
1#
#1340000000
0!
0#
#1345000000
1!
1#
b10 %
b0 &
#1350000000
0!
0#
#1355000000
1!
1#
b1 &
b0 '
#1360000000
0!
0#
#1365000000
1!
1#
b1111 '
#1370000000
0!
0#
#1375000000
1!
1#
#1380000000
0!
0#
#1385000000
1!
1#
#1390000000
0!
0#
#1395000000
1!
1#
b10 &
b0 '
#1400000000
0!
0#
#1405000000
1!
1#
b1111 '
#1410000000
0!
0#
#1415000000
1!
1#
#1420000000
0!
0#
#1425000000
1!
1#
#1430000000
0!
0#
#1435000000
1!
1#
b11 &
b0 '
#1440000000
0!
0#
#1445000000
1!
1#
b1111 '
#1450000000
0!
0#
#1455000000
1!
1#
#1460000000
0!
0#
#1465000000
1!
1#
#1470000000
0!
0#
#1475000000
1!
1#
b100 &
b0 '
#1480000000
0!
0#
#1485000000
1!
1#
b1111 '
#1490000000
0!
0#
#1495000000
1!
1#
#1500000000
0!
0#
#1505000000
1!
1#
#1510000000
0!
0#
#1515000000
1!
1#
b101 &
b0 '
#1520000000
0!
0#
#1525000000
1!
1#
b1111 '
#1530000000
0!
0#
#1535000000
1!
1#
#1540000000
0!
0#
#1545000000
1!
1#
#1550000000
0!
0#
#1555000000
1!
1#
b110 &
b0 '
#1560000000
0!
0#
#1565000000
1!
1#
b1111 '
#1570000000
0!
0#
#1575000000
1!
1#
#1580000000
0!
0#
#1585000000
1!
1#
#1590000000
0!
0#
#1595000000
1!
1#
b111 &
b0 '
#1600000000
0!
0#
#1605000000
1!
1#
b1111 '
#1610000000
0!
0#
#1615000000
1!
1#
#1620000000
0!
0#
#1625000000
1!
1#
#1630000000
0!
0#
#1635000000
1!
1#
b1000 &
b0 '
#1640000000
0!
0#
#1645000000
1!
1#
b1111 '
#1650000000
0!
0#
#1655000000
1!
1#
#1660000000
0!
0#
#1665000000
1!
1#
#1670000000
0!
0#
#1675000000
1!
1#
b1001 &
b0 '
#1680000000
0!
0#
#1685000000
1!
1#
b1111 '
#1690000000
0!
0#
#1695000000
1!
1#
#1700000000
0!
0#
#1705000000
1!
1#
#1710000000
0!
0#
#1715000000
1!
1#
b1010 &
b0 '
#1720000000
0!
0#
#1725000000
1!
1#
b1111 '
#1730000000
0!
0#
#1735000000
1!
1#
#1740000000
0!
0#
#1745000000
1!
1#
#1750000000
0!
0#
#1755000000
1!
1#
b1011 &
b0 '
#1760000000
0!
0#
#1765000000
1!
1#
b1111 '
#1770000000
0!
0#
#1775000000
1!
1#
#1780000000
0!
0#
#1785000000
1!
1#
#1790000000
0!
0#
#1795000000
1!
1#
b1100 &
b0 '
#1800000000
0!
0#
#1805000000
1!
1#
b1111 '
#1810000000
0!
0#
#1815000000
1!
1#
#1820000000
0!
0#
#1825000000
1!
1#
#1830000000
0!
0#
#1835000000
1!
1#
b1101 &
b0 '
#1840000000
0!
0#
#1845000000
1!
1#
b1111 '
#1850000000
0!
0#
#1855000000
1!
1#
#1860000000
0!
0#
#1865000000
1!
1#
#1870000000
0!
0#
#1875000000
1!
1#
b1110 &
b0 '
#1880000000
0!
0#
#1885000000
1!
1#
b1111 '
#1890000000
0!
0#
#1895000000
1!
1#
#1900000000
0!
0#
#1905000000
1!
1#
#1910000000
0!
0#
#1915000000
1!
1#
b1111 &
b0 '
#1920000000
0!
0#
#1925000000
1!
1#
b1111 '
#1930000000
0!
0#
#1935000000
1!
1#
#1940000000
0!
0#
#1945000000
1!
1#
#1950000000
0!
0#
#1955000000
1!
1#
#1960000000
0!
0#
#1965000000
1!
1#
b11 %
b0 &
#1970000000
0!
0#
#1975000000
1!
1#
b1 &
b0 '
#1980000000
0!
0#
#1985000000
1!
1#
b1111 '
#1990000000
0!
0#
#1995000000
1!
1#
#2000000000
0!
0#
#2005000000
1!
1#
#2010000000
0!
0#
#2015000000
1!
1#
b10 &
b0 '
#2020000000
0!
0#
#2025000000
1!
1#
b1111 '
#2030000000
0!
0#
#2035000000
1!
1#
#2040000000
0!
0#
#2045000000
1!
1#
#2050000000
0!
0#
#2055000000
1!
1#
b11 &
b0 '
#2060000000
0!
0#
#2065000000
1!
1#
b1111 '
#2070000000
0!
0#
#2075000000
1!
1#
#2080000000
0!
0#
#2085000000
1!
1#
#2090000000
0!
0#
#2095000000
1!
1#
b100 &
b0 '
#2100000000
0!
0#
#2105000000
1!
1#
b1111 '
#2110000000
0!
0#
#2115000000
1!
1#
#2120000000
0!
0#
#2125000000
1!
1#
#2130000000
0!
0#
#2135000000
1!
1#
b101 &
b0 '
#2140000000
0!
0#
#2145000000
1!
1#
b1111 '
#2150000000
0!
0#
#2155000000
1!
1#
#2160000000
0!
0#
#2165000000
1!
1#
#2170000000
0!
0#
#2175000000
1!
1#
b110 &
b0 '
#2180000000
0!
0#
#2185000000
1!
1#
b1111 '
#2190000000
0!
0#
#2195000000
1!
1#
#2200000000
0!
0#
#2205000000
1!
1#
#2210000000
0!
0#
#2215000000
1!
1#
b111 &
b0 '
#2220000000
0!
0#
#2225000000
1!
1#
b1111 '
#2230000000
0!
0#
#2235000000
1!
1#
#2240000000
0!
0#
#2245000000
1!
1#
#2250000000
0!
0#
#2255000000
1!
1#
b1000 &
b0 '
#2260000000
0!
0#
#2265000000
1!
1#
b1111 '
#2270000000
0!
0#
#2275000000
1!
1#
#2280000000
0!
0#
#2285000000
1!
1#
#2290000000
0!
0#
#2295000000
1!
1#
b1001 &
b0 '
#2300000000
0!
0#
#2305000000
1!
1#
b1111 '
#2310000000
0!
0#
#2315000000
1!
1#
#2320000000
0!
0#
#2325000000
1!
1#
#2330000000
0!
0#
#2335000000
1!
1#
b1010 &
b0 '
#2340000000
0!
0#
#2345000000
1!
1#
b1111 '
#2350000000
0!
0#
#2355000000
1!
1#
#2360000000
0!
0#
#2365000000
1!
1#
#2370000000
0!
0#
#2375000000
1!
1#
b1011 &
b0 '
#2380000000
0!
0#
#2385000000
1!
1#
b1111 '
#2390000000
0!
0#
#2395000000
1!
1#
#2400000000
0!
0#
#2405000000
1!
1#
#2410000000
0!
0#
#2415000000
1!
1#
b1100 &
b0 '
#2420000000
0!
0#
#2425000000
1!
1#
b1111 '
#2430000000
0!
0#
#2435000000
1!
1#
#2440000000
0!
0#
#2445000000
1!
1#
#2450000000
0!
0#
#2455000000
1!
1#
b1101 &
b0 '
#2460000000
0!
0#
#2465000000
1!
1#
b1111 '
#2470000000
0!
0#
#2475000000
1!
1#
#2480000000
0!
0#
#2485000000
1!
1#
#2490000000
0!
0#
#2495000000
1!
1#
b1110 &
b0 '
#2500000000
0!
0#
#2505000000
1!
1#
b1111 '
#2510000000
0!
0#
#2515000000
1!
1#
#2520000000
0!
0#
#2525000000
1!
1#
#2530000000
0!
0#
#2535000000
1!
1#
b1111 &
b0 '
#2540000000
0!
0#
#2545000000
1!
1#
b1111 '
#2550000000
0!
0#
#2555000000
1!
1#
#2560000000
0!
0#
#2565000000
1!
1#
#2570000000
0!
0#
#2575000000
1!
1#
#2580000000
0!
0#
#2585000000
1!
1#
b100 %
b0 &
#2590000000
0!
0#
#2595000000
1!
1#
b1 &
b0 '
#2600000000
0!
0#
#2605000000
1!
1#
b1111 '
#2610000000
0!
0#
#2615000000
1!
1#
#2620000000
0!
0#
#2625000000
1!
1#
#2630000000
0!
0#
#2635000000
1!
1#
b10 &
b0 '
#2640000000
0!
0#
#2645000000
1!
1#
b1111 '
#2650000000
0!
0#
#2655000000
1!
1#
#2660000000
0!
0#
#2665000000
1!
1#
#2670000000
0!
0#
#2675000000
1!
1#
b11 &
b0 '
#2680000000
0!
0#
#2685000000
1!
1#
b1111 '
#2690000000
0!
0#
#2695000000
1!
1#
#2700000000
0!
0#
#2705000000
1!
1#
#2710000000
0!
0#
#2715000000
1!
1#
b100 &
b0 '
#2720000000
0!
0#
#2725000000
1!
1#
b1111 '
#2730000000
0!
0#
#2735000000
1!
1#
#2740000000
0!
0#
#2745000000
1!
1#
#2750000000
0!
0#
#2755000000
1!
1#
b101 &
b0 '
#2760000000
0!
0#
#2765000000
1!
1#
b1111 '
#2770000000
0!
0#
#2775000000
1!
1#
#2780000000
0!
0#
#2785000000
1!
1#
#2790000000
0!
0#
#2795000000
1!
1#
b110 &
b0 '
#2800000000
0!
0#
#2805000000
1!
1#
b1111 '
#2810000000
0!
0#
#2815000000
1!
1#
#2820000000
0!
0#
#2825000000
1!
1#
#2830000000
0!
0#
#2835000000
1!
1#
b111 &
b0 '
#2840000000
0!
0#
#2845000000
1!
1#
b1111 '
#2850000000
0!
0#
#2855000000
1!
1#
#2860000000
0!
0#
#2865000000
1!
1#
#2870000000
0!
0#
#2875000000
1!
1#
b1000 &
b0 '
#2880000000
0!
0#
#2885000000
1!
1#
b1111 '
#2890000000
0!
0#
#2895000000
1!
1#
#2900000000
0!
0#
#2905000000
1!
1#
#2910000000
0!
0#
#2915000000
1!
1#
b1001 &
b0 '
#2920000000
0!
0#
#2925000000
1!
1#
b1111 '
#2930000000
0!
0#
#2935000000
1!
1#
#2940000000
0!
0#
#2945000000
1!
1#
#2950000000
0!
0#
#2955000000
1!
1#
b1010 &
b0 '
#2960000000
0!
0#
#2965000000
1!
1#
b1111 '
#2970000000
0!
0#
#2975000000
1!
1#
#2980000000
0!
0#
#2985000000
1!
1#
#2990000000
0!
0#
#2995000000
1!
1#
b1011 &
b0 '
#3000000000
0!
0#
#3005000000
1!
1#
b1111 '
#3010000000
0!
0#
#3015000000
1!
1#
#3020000000
0!
0#
#3025000000
1!
1#
#3030000000
0!
0#
#3035000000
1!
1#
b1100 &
b0 '
#3040000000
0!
0#
#3045000000
1!
1#
b1111 '
#3050000000
0!
0#
#3055000000
1!
1#
#3060000000
0!
0#
#3065000000
1!
1#
#3070000000
0!
0#
#3075000000
1!
1#
b1101 &
b0 '
#3080000000
0!
0#
#3085000000
1!
1#
b1111 '
#3090000000
0!
0#
#3095000000
1!
1#
#3100000000
0!
0#
#3105000000
1!
1#
#3110000000
0!
0#
#3115000000
1!
1#
b1110 &
b0 '
#3120000000
0!
0#
#3125000000
1!
1#
b1111 '
#3130000000
0!
0#
#3135000000
1!
1#
#3140000000
0!
0#
#3145000000
1!
1#
#3150000000
0!
0#
#3155000000
1!
1#
b1111 &
b0 '
#3160000000
0!
0#
#3165000000
1!
1#
b1111 '
#3170000000
0!
0#
#3175000000
1!
1#
#3180000000
0!
0#
#3185000000
1!
1#
#3190000000
0!
0#
#3195000000
1!
1#
#3200000000
0!
0#
#3205000000
1!
1#
b101 %
b0 &
#3210000000
0!
0#
#3215000000
1!
1#
b1 &
b0 '
#3220000000
0!
0#
#3225000000
1!
1#
b1111 '
#3230000000
0!
0#
#3235000000
1!
1#
#3240000000
0!
0#
#3245000000
1!
1#
#3250000000
0!
0#
#3255000000
1!
1#
b10 &
b0 '
#3260000000
0!
0#
#3265000000
1!
1#
b1111 '
#3270000000
0!
0#
#3275000000
1!
1#
#3280000000
0!
0#
#3285000000
1!
1#
#3290000000
0!
0#
#3295000000
1!
1#
b11 &
b0 '
#3300000000
0!
0#
#3305000000
1!
1#
b1111 '
#3310000000
0!
0#
#3315000000
1!
1#
#3320000000
0!
0#
#3325000000
1!
1#
#3330000000
0!
0#
#3335000000
1!
1#
b100 &
b0 '
#3340000000
0!
0#
#3345000000
1!
1#
b1111 '
#3350000000
0!
0#
#3355000000
1!
1#
#3360000000
0!
0#
#3365000000
1!
1#
#3370000000
0!
0#
#3375000000
1!
1#
b101 &
b0 '
#3380000000
0!
0#
#3385000000
1!
1#
b1111 '
#3390000000
0!
0#
#3395000000
1!
1#
#3400000000
0!
0#
#3405000000
1!
1#
#3410000000
0!
0#
#3415000000
1!
1#
b110 &
b0 '
#3420000000
0!
0#
#3425000000
1!
1#
b1111 '
#3430000000
0!
0#
#3435000000
1!
1#
#3440000000
0!
0#
#3445000000
1!
1#
#3450000000
0!
0#
#3455000000
1!
1#
b111 &
b0 '
#3460000000
0!
0#
#3465000000
1!
1#
b1111 '
#3470000000
0!
0#
#3475000000
1!
1#
#3480000000
0!
0#
#3485000000
1!
1#
#3490000000
0!
0#
#3495000000
1!
1#
b1000 &
b0 '
#3500000000
0!
0#
#3505000000
1!
1#
b1111 '
#3510000000
0!
0#
#3515000000
1!
1#
#3520000000
0!
0#
#3525000000
1!
1#
#3530000000
0!
0#
#3535000000
1!
1#
b1001 &
b0 '
#3540000000
0!
0#
#3545000000
1!
1#
b1111 '
#3550000000
0!
0#
#3555000000
1!
1#
#3560000000
0!
0#
#3565000000
1!
1#
#3570000000
0!
0#
#3575000000
1!
1#
b1010 &
b0 '
#3580000000
0!
0#
#3585000000
1!
1#
b1111 '
#3590000000
0!
0#
#3595000000
1!
1#
